doodah/__init__.py
doodah/doodah.py
doodah-0.0.1.dist-info/LICENSE
doodah-0.0.1.dist-info/METADATA
doodah-0.0.1.dist-info/WHEEL
doodah-0.0.1.dist-info/top_level.txt
doodah-0.0.1.dist-info/RECORD
