Metadata-Version: 2.1
Name: doodah
Version: 0.0.1
Summary: Web dashboard
Home-page: https://github.com/Scaremonger/doodah
Author: Si Dunford
Author-email: dunford.sj@gmail.com
License: UNKNOWN
Platform: UNKNOWN
Classifier: Programming Language :: Python :: 3
Classifier: License :: OSI Approved :: MIT License
Classifier: Operating System :: OS Independent
